Metadata-Version: 2.1
Name: zato-ext-inotifyx
Version: 0.3
Summary: Simple Linux inotify bindings
Home-page: https://launchpad.net/inotifyx/
Author: Forest Bond
Author-email: forest@forestbond.com
License-File: COPYING
License-File: AUTHORS
